[
    {
        "division": "AFC East",
        "teams": [
            {
                "team": "Buffalo Bills*",
                "W": "13",
                "L": "3",
                "PD": "164"
            },
            {
                "team": "Miami Dolphins",
                "W": "8",
                "L": "8",
                "PD": "-7"
            },
            {
                "team": "New York Jets",
                "W": "4",
                "L": "12",
                "PD": "-78"
            },
            {
                "team": "New England Patriots",
                "W": "3",
                "L": "13",
                "PD": "-135"
            }
        ]
    },
    {
        "division": "AFC North",
        "teams": [
            {
                "team": "Baltimore Ravens*",
                "W": "12",
                "L": "5",
                "PD": "157"
            },
            {
                "team": "Pittsburgh Steelers+",
                "W": "10",
                "L": "7",
                "PD": "33"
            },
            {
                "team": "Cincinnati Bengals",
                "W": "9",
                "L": "8",
                "PD": "38"
            },
            {
                "team": "Cleveland Browns",
                "W": "3",
                "L": "14",
                "PD": "-177"
            }
        ]
    },
    {
        "division": "AFC South",
        "teams": [
            {
                "team": "Houston Texans*",
                "W": "9",
                "L": "7",
                "PD": "-9"
            },
            {
                "team": "Indianapolis Colts",
                "W": "7",
                "L": "9",
                "PD": "-53"
            },
            {
                "team": "Jacksonville Jaguars",
                "W": "4",
                "L": "12",
                "PD": "-112"
            },
            {
                "team": "Tennessee Titans",
                "W": "3",
                "L": "13",
                "PD": "-140"
            }
        ]
    },
    {
        "division": "AFC West",
        "teams": [
            {
                "team": "Kansas City Chiefs*",
                "W": "15",
                "L": "1",
                "PD": "97"
            },
            {
                "team": "Los Angeles Chargers+",
                "W": "10",
                "L": "6",
                "PD": "87"
            },
            {
                "team": "Denver Broncos+",
                "W": "9",
                "L": "7",
                "PD": "76"
            },
            {
                "team": "Las Vegas Raiders",
                "W": "4",
                "L": "12",
                "PD": "-111"
            }
        ]
    },
    {
        "division": "NFC East",
        "teams": [
            {
                "team": "Philadelphia Eagles*",
                "W": "13",
                "L": "3",
                "PD": "153"
            },
            {
                "team": "Washington Commanders+",
                "W": "11",
                "L": "5",
                "PD": "90"
            },
            {
                "team": "Dallas Cowboys",
                "W": "7",
                "L": "9",
                "PD": "-114"
            },
            {
                "team": "New York Giants",
                "W": "3",
                "L": "13",
                "PD": "-135"
            }
        ]
    },
    {
        "division": "NFC North",
        "teams": [
            {
                "team": "Detroit Lions*",
                "W": "14",
                "L": "2",
                "PD": "200"
            },
            {
                "team": "Minnesota Vikings*",
                "W": "14",
                "L": "2",
                "PD": "122"
            },
            {
                "team": "Green Bay Packers+",
                "W": "11",
                "L": "5",
                "PD": "124"
            },
            {
                "team": "Chicago Bears",
                "W": "4",
                "L": "12",
                "PD": "-62"
            }
        ]
    },
    {
        "division": "NFC South",
        "teams": [
            {
                "team": "Tampa Bay Buccaneers*",
                "W": "9",
                "L": "7",
                "PD": "109"
            },
            {
                "team": "Atlanta Falcons",
                "W": "8",
                "L": "8",
                "PD": "-28"
            },
            {
                "team": "New Orleans Saints",
                "W": "5",
                "L": "11",
                "PD": "-52"
            },
            {
                "team": "Carolina Panthers",
                "W": "4",
                "L": "12",
                "PD": "-199"
            }
        ]
    },
    {
        "division": "NFC West",
        "teams": [
            {
                "team": "Los Angeles Rams*",
                "W": "10",
                "L": "6",
                "PD": "-14"
            },
            {
                "team": "Seattle Seahawks",
                "W": "9",
                "L": "7",
                "PD": "2"
            },
            {
                "team": "Arizona Cardinals",
                "W": "7",
                "L": "9",
                "PD": "-2"
            },
            {
                "team": "San Francisco 49ers",
                "W": "6",
                "L": "10",
                "PD": "-24"
            }
        ]
    }
]